athetes_unlimited_py/__init__.py
athetes_unlimited_py/aux_softball.py
athetes_unlimited_py/basketball.py
athetes_unlimited_py/lacrosse.py
athetes_unlimited_py/softball.py
athetes_unlimited_py/utils.py
athetes_unlimited_py/volleyball.py
athletes_unlimited_py-0.0.8.dist-info/LICENSE
athletes_unlimited_py-0.0.8.dist-info/METADATA
athletes_unlimited_py-0.0.8.dist-info/WHEEL
athletes_unlimited_py-0.0.8.dist-info/top_level.txt
athletes_unlimited_py-0.0.8.dist-info/RECORD
